gridfs_storage/__init__.py
gridfs_storage/apps.py
gridfs_storage/storage.py
gridfs_storage/urls.py
gridfs_storage/views.py
django_gridfs_storage-0.0.2.dist-info/LICENSE
django_gridfs_storage-0.0.2.dist-info/METADATA
django_gridfs_storage-0.0.2.dist-info/WHEEL
django_gridfs_storage-0.0.2.dist-info/top_level.txt
django_gridfs_storage-0.0.2.dist-info/RECORD
