Metadata-Version: 2.1
Name: django-gridfs-storage
Version: 0.0.2
Summary: Django GridFS Storage Engine
Home-page: https://github.com/kingjmk/django-gridfs-storage
Author: Jameel Hamdan
Author-email: jameelhamdan99@yahoo.com
License: MIT
Platform: UNKNOWN
Classifier: Framework :: Django
Classifier: Framework :: Django :: 2.2
Classifier: Framework :: Django :: 3.1
Classifier: Programming Language :: Python
Classifier: Programming Language :: Python :: 3.7
Classifier: Programming Language :: Python :: 3.8
Classifier: Development Status :: 3 - Alpha
Classifier: License :: OSI Approved :: MIT License
Requires-Python: >3.6
